MANIFEST.in
README.txt
setup.cfg
setup.py
src/requires.txt
src/m3_calendar/__init__.py
src/m3_calendar/actions.py
src/m3_calendar/api.py
src/m3_calendar/app_meta.py
src/m3_calendar/controller.py
src/m3_calendar/models.py
src/m3_calendar/ui.py
src/m3_calendar/version.py
src/m3_calendar.egg-info/PKG-INFO
src/m3_calendar.egg-info/SOURCES.txt
src/m3_calendar.egg-info/dependency_links.txt
src/m3_calendar.egg-info/top_level.txt
src/m3_calendar/migrations/0001_initial.py
src/m3_calendar/migrations/__init__.py
src/m3_calendar/templates/showM3Calendar.js
src/tests/__init__.py
src/tests/manage.py
src/tests/prepare_env.py
src/tests/settings.py
src/tests/shell.sh
src/tests/test.sh
src/tests/urls.py
src/tests/version.py
src/tests/core/__init__.py
src/tests/core/tests.py